{
  "generated_at": "2026-07-07 12:49:49",
  "latest_trade_date": "2026-07-07",
  "summary": [
    {
      "date": "2026-07-07",
      "up_count": null,
      "down_count": null,
      "flat_count": null,
      "limit_up_count": 33,
      "limit_down_count": 30
    },
    {
      "date": "2026-07-06",
      "up_count": 1876,
      "down_count": 3141,
      "flat_count": 100,
      "limit_up_count": 8,
      "limit_down_count": 46
    },
    {
      "date": "2026-07-03",
      "up_count": 2604,
      "down_count": 1628,
      "flat_count": 84,
      "limit_up_count": 3,
      "limit_down_count": 24
    }
  ],
  "limit_up_details_by_date": {
    "2026-07-03": [
      {
        "code": "603178",
        "name": "圣龙股份",
        "reason": "机器人关节驱动+飞行汽车+泵类龙头",
        "concepts": [
          "减速器",
          "汽车热管理",
          "飞行汽车(eVTOL)",
          "机器人概念",
          "低空经济",
          "长安汽车概念",
          "共同富裕示范区",
          "数字经济",
          "无人驾驶",
          "华为汽车",
          "新能源汽车",
          "比亚迪概念",
          "融资融券",
          "沪股通"
        ],
        "amount": 147152966.0,
        "turnover_rate": 3.89,
        "first_limit_up_time": "09:35:53",
        "last_limit_up_time": "09:35:53",
        "consecutive_boards": 1
      },
      {
        "code": "600793",
        "name": "宜宾纸业",
        "reason": "TAC膜+醋酸纤维素+竹基新材料+宜宾国资",
        "concepts": [
          "西部大开发",
          "国企改革",
          "食品安全",
          "电子纸"
        ],
        "amount": 321315285.32,
        "turnover_rate": 9.55,
        "first_limit_up_time": "09:46:37",
        "last_limit_up_time": "09:46:37",
        "consecutive_boards": 5
      },
      {
        "code": "603137",
        "name": "恒尚节能",
        "reason": "拟收购存储公司+建筑幕墙+跨界转型",
        "concepts": [
          "装配式建筑",
          "建筑节能",
          "新型城镇化",
          "光伏建筑一体化",
          "股权转让(并购重组)",
          "融资融券"
        ],
        "amount": 15183966.01,
        "turnover_rate": 0.4,
        "first_limit_up_time": "09:25:03",
        "last_limit_up_time": "09:25:03",
        "consecutive_boards": 6
      }
    ],
    "2026-07-06": [
      {
        "code": "600793",
        "name": "宜宾纸业",
        "reason": "TAC膜+醋酸纤维素+竹基新材料+宜宾国资",
        "concepts": [
          "西部大开发",
          "国企改革",
          "食品安全",
          "电子纸"
        ],
        "amount": 321315285.32,
        "turnover_rate": 9.55,
        "first_limit_up_time": "09:46:37",
        "last_limit_up_time": "09:46:37",
        "consecutive_boards": 5
      },
      {
        "code": "600246",
        "name": "万通发展",
        "reason": "高速交换芯片+AI算力+PCIe5.0量产",
        "concepts": [
          "存储芯片",
          "芯片概念",
          "5G",
          "毫米波雷达",
          "卫星导航",
          "商业航天",
          "创投",
          "数字经济",
          "京津冀一体化",
          "物业管理",
          "云计算",
          "沪股通",
          "融资融券"
        ],
        "amount": 4641981027.08,
        "turnover_rate": 13.4,
        "first_limit_up_time": "09:48:16",
        "last_limit_up_time": "15:07:34",
        "consecutive_boards": 2
      },
      {
        "code": "603861",
        "name": "白云电器",
        "reason": "变压器出海+AIDC直流配电+电网设备",
        "concepts": [
          "柔性直流输电",
          "智能电网",
          "华为数字能源",
          "特高压",
          "东数西算(算力)",
          "核电",
          "数据中心(AIDC)",
          "一带一路",
          "储能",
          "华为概念",
          "新能源汽车",
          "光伏概念",
          "宁德时代概念",
          "沪股通"
        ],
        "amount": 667597133.35,
        "turnover_rate": 8.51,
        "first_limit_up_time": "09:51:21",
        "last_limit_up_time": "10:01:33",
        "consecutive_boards": 2
      },
      {
        "code": "603137",
        "name": "恒尚节能",
        "reason": "拟收购存储公司+建筑幕墙+跨界转型",
        "concepts": [
          "装配式建筑",
          "建筑节能",
          "新型城镇化",
          "光伏建筑一体化",
          "股权转让(并购重组)",
          "融资融券"
        ],
        "amount": 15183966.01,
        "turnover_rate": 0.4,
        "first_limit_up_time": "09:25:03",
        "last_limit_up_time": "09:25:03",
        "consecutive_boards": 6
      },
      {
        "code": "600288",
        "name": "大恒科技",
        "reason": "机器视觉+机器人+半导体",
        "concepts": [
          "太赫兹",
          "量子科技",
          "机器视觉",
          "专精特新",
          "无人机",
          "6G概念",
          "机器人概念",
          "华为概念",
          "人工智能",
          "元宇宙",
          "芯片概念",
          "腾讯概念",
          "数据要素",
          "AIGC概念",
          "京津冀一体化",
          "智能医疗",
          "宁德时代概念",
          "AI视频",
          "虚拟数字人",
          "华为手机",
          "眼科医疗",
          "期货概念",
          "融资融券",
          "沪股通"
        ],
        "amount": 1869913047.01,
        "turnover_rate": 27.84,
        "first_limit_up_time": "09:34:06",
        "last_limit_up_time": "14:51:48",
        "consecutive_boards": 2
      },
      {
        "code": "002457",
        "name": "青龙管业",
        "reason": "其他",
        "concepts": [
          "地下管网",
          "新型城镇化",
          "水利",
          "乡村振兴",
          "参股银行",
          "京津冀一体化",
          "互联网金融",
          "新疆振兴",
          "西部大开发",
          "风电"
        ],
        "amount": 1383427145.57,
        "turnover_rate": 27.74,
        "first_limit_up_time": "09:30:27",
        "last_limit_up_time": "09:30:27",
        "consecutive_boards": 0
      },
      {
        "code": "603722",
        "name": "阿科力",
        "reason": "其他",
        "concepts": [
          "丙烯酸",
          "专精特新",
          "人民币贬值受益",
          "燃料电池"
        ],
        "amount": 881085542.32,
        "turnover_rate": 19.64,
        "first_limit_up_time": "09:25:03",
        "last_limit_up_time": "09:32:27",
        "consecutive_boards": 0
      },
      {
        "code": "603819",
        "name": "神力股份",
        "reason": "其他",
        "concepts": [
          "安防",
          "新能源汽车",
          "风电",
          "股权转让(并购重组)"
        ],
        "amount": 539335355.3,
        "turnover_rate": 17.24,
        "first_limit_up_time": "09:31:11",
        "last_limit_up_time": "09:48:38",
        "consecutive_boards": 0
      }
    ],
    "2026-07-07": [
      {
        "code": "002497",
        "name": "雅化集团",
        "reason": "化学制品",
        "concepts": [],
        "amount": 437457072.0,
        "turnover_rate": 1.67,
        "first_limit_up_time": "09:25:00",
        "last_limit_up_time": "09:25:00",
        "consecutive_boards": 1
      },
      {
        "code": "002841",
        "name": "视源股份",
        "reason": "消费电子",
        "concepts": [],
        "amount": 238093079.0,
        "turnover_rate": 1.06,
        "first_limit_up_time": "09:25:00",
        "last_limit_up_time": "09:25:00",
        "consecutive_boards": 1
      },
      {
        "code": "301251",
        "name": "威尔高",
        "reason": "元件",
        "concepts": [],
        "amount": 214899764.0,
        "turnover_rate": 5.6,
        "first_limit_up_time": "09:25:00",
        "last_limit_up_time": "09:25:00",
        "consecutive_boards": 1
      },
      {
        "code": "601121",
        "name": "宝地矿业",
        "reason": "冶钢原料",
        "concepts": [],
        "amount": 50482822.0,
        "turnover_rate": 0.98,
        "first_limit_up_time": "09:25:02",
        "last_limit_up_time": "09:25:02",
        "consecutive_boards": 1
      },
      {
        "code": "600120",
        "name": "浙江东方",
        "reason": "多元金融",
        "concepts": [],
        "amount": 141849205.0,
        "turnover_rate": 0.85,
        "first_limit_up_time": "09:25:03",
        "last_limit_up_time": "09:25:03",
        "consecutive_boards": 1
      },
      {
        "code": "603137",
        "name": "恒尚节能",
        "reason": "装修装饰",
        "concepts": [],
        "amount": 15183966.0,
        "turnover_rate": 0.4,
        "first_limit_up_time": "09:25:03",
        "last_limit_up_time": "09:25:03",
        "consecutive_boards": 6
      },
      {
        "code": "001229",
        "name": "魅视科技",
        "reason": "计算机设",
        "concepts": [],
        "amount": 70328792.0,
        "turnover_rate": 2.47,
        "first_limit_up_time": "09:30:06",
        "last_limit_up_time": "09:30:06",
        "consecutive_boards": 1
      },
      {
        "code": "000973",
        "name": "佛塑科技",
        "reason": "塑料",
        "concepts": [],
        "amount": 1442843984.0,
        "turnover_rate": 10.3,
        "first_limit_up_time": "09:31:03",
        "last_limit_up_time": "13:45:03",
        "consecutive_boards": 1
      },
      {
        "code": "001311",
        "name": "多利科技",
        "reason": "汽车零部",
        "concepts": [],
        "amount": 66098081.0,
        "turnover_rate": 1.94,
        "first_limit_up_time": "09:31:45",
        "last_limit_up_time": "09:31:45",
        "consecutive_boards": 1
      },
      {
        "code": "600288",
        "name": "大恒科技",
        "reason": "软件开发",
        "concepts": [],
        "amount": 1869913040.0,
        "turnover_rate": 27.84,
        "first_limit_up_time": "09:34:06",
        "last_limit_up_time": "14:51:48",
        "consecutive_boards": 2
      },
      {
        "code": "002951",
        "name": "金时科技",
        "reason": "其他电源",
        "concepts": [],
        "amount": 87552170.0,
        "turnover_rate": 1.5,
        "first_limit_up_time": "09:35:03",
        "last_limit_up_time": "09:35:03",
        "consecutive_boards": 1
      },
      {
        "code": "603356",
        "name": "华菱精工",
        "reason": "专用设备",
        "concepts": [],
        "amount": 87877445.0,
        "turnover_rate": 3.74,
        "first_limit_up_time": "09:35:26",
        "last_limit_up_time": "09:35:26",
        "consecutive_boards": 1
      },
      {
        "code": "603178",
        "name": "圣龙股份",
        "reason": "汽车零部",
        "concepts": [],
        "amount": 147152966.0,
        "turnover_rate": 3.89,
        "first_limit_up_time": "09:35:53",
        "last_limit_up_time": "09:35:53",
        "consecutive_boards": 1
      },
      {
        "code": "603065",
        "name": "宿迁联盛",
        "reason": "化学制品",
        "concepts": [],
        "amount": 1350738528.0,
        "turnover_rate": 16.49,
        "first_limit_up_time": "09:37:32",
        "last_limit_up_time": "14:40:50",
        "consecutive_boards": 1
      },
      {
        "code": "605118",
        "name": "力鼎光电",
        "reason": "计算机设",
        "concepts": [],
        "amount": 204689356.0,
        "turnover_rate": 1.33,
        "first_limit_up_time": "09:37:35",
        "last_limit_up_time": "09:40:08",
        "consecutive_boards": 1
      },
      {
        "code": "001365",
        "name": "天海电子",
        "reason": "汽车零部",
        "concepts": [],
        "amount": 337661968.0,
        "turnover_rate": 13.72,
        "first_limit_up_time": "09:38:18",
        "last_limit_up_time": "09:38:18",
        "consecutive_boards": 1
      },
      {
        "code": "002585",
        "name": "双星新材",
        "reason": "塑料",
        "concepts": [],
        "amount": 481444992.0,
        "turnover_rate": 4.92,
        "first_limit_up_time": "09:43:15",
        "last_limit_up_time": "09:43:15",
        "consecutive_boards": 1
      },
      {
        "code": "600206",
        "name": "有研新材",
        "reason": "半导体",
        "concepts": [],
        "amount": 4559045888.0,
        "turnover_rate": 9.85,
        "first_limit_up_time": "09:45:36",
        "last_limit_up_time": "11:26:33",
        "consecutive_boards": 1
      },
      {
        "code": "600793",
        "name": "宜宾纸业",
        "reason": "造纸",
        "concepts": [],
        "amount": 321315280.0,
        "turnover_rate": 9.55,
        "first_limit_up_time": "09:46:37",
        "last_limit_up_time": "09:46:37",
        "consecutive_boards": 5
      },
      {
        "code": "600246",
        "name": "万通发展",
        "reason": "房地产开",
        "concepts": [],
        "amount": 4641980928.0,
        "turnover_rate": 13.4,
        "first_limit_up_time": "09:48:16",
        "last_limit_up_time": "15:00:00",
        "consecutive_boards": 2
      },
      {
        "code": "603861",
        "name": "白云电器",
        "reason": "电网设备",
        "concepts": [],
        "amount": 667597136.0,
        "turnover_rate": 8.51,
        "first_limit_up_time": "09:51:21",
        "last_limit_up_time": "10:01:33",
        "consecutive_boards": 2
      },
      {
        "code": "001206",
        "name": "依依股份",
        "reason": "个护用品",
        "concepts": [],
        "amount": 154515203.0,
        "turnover_rate": 7.6,
        "first_limit_up_time": "09:52:30",
        "last_limit_up_time": "09:52:30",
        "consecutive_boards": 1
      },
      {
        "code": "002137",
        "name": "实益达",
        "reason": "光学光电",
        "concepts": [],
        "amount": 1120029792.0,
        "turnover_rate": 25.26,
        "first_limit_up_time": "09:53:57",
        "last_limit_up_time": "13:13:54",
        "consecutive_boards": 1
      },
      {
        "code": "688432",
        "name": "有研硅",
        "reason": "半导体",
        "concepts": [],
        "amount": 3389040400.0,
        "turnover_rate": 6.12,
        "first_limit_up_time": "09:56:40",
        "last_limit_up_time": "14:18:40",
        "consecutive_boards": 1
      },
      {
        "code": "002129",
        "name": "TCL中环",
        "reason": "光伏设备",
        "concepts": [],
        "amount": 3797452160.0,
        "turnover_rate": 8.74,
        "first_limit_up_time": "10:05:24",
        "last_limit_up_time": "13:26:57",
        "consecutive_boards": 1
      },
      {
        "code": "301516",
        "name": "中远通",
        "reason": "其他电源",
        "concepts": [],
        "amount": 417897952.0,
        "turnover_rate": 33.32,
        "first_limit_up_time": "10:09:33",
        "last_limit_up_time": "13:16:09",
        "consecutive_boards": 1
      },
      {
        "code": "605399",
        "name": "晨光新材",
        "reason": "化学制品",
        "concepts": [],
        "amount": 144535988.0,
        "turnover_rate": 3.31,
        "first_limit_up_time": "10:22:21",
        "last_limit_up_time": "10:22:21",
        "consecutive_boards": 1
      },
      {
        "code": "002185",
        "name": "华天科技",
        "reason": "半导体",
        "concepts": [],
        "amount": 11999102720.0,
        "turnover_rate": 16.93,
        "first_limit_up_time": "10:30:15",
        "last_limit_up_time": "13:16:18",
        "consecutive_boards": 1
      },
      {
        "code": "603823",
        "name": "百合花",
        "reason": "化学制品",
        "concepts": [],
        "amount": 2118297984.0,
        "turnover_rate": 7.22,
        "first_limit_up_time": "10:35:06",
        "last_limit_up_time": "14:55:06",
        "consecutive_boards": 1
      },
      {
        "code": "600094",
        "name": "大名城",
        "reason": "房地产开",
        "concepts": [],
        "amount": 122700371.0,
        "turnover_rate": 1.57,
        "first_limit_up_time": "10:58:33",
        "last_limit_up_time": "10:58:33",
        "consecutive_boards": 1
      },
      {
        "code": "003004",
        "name": "声迅股份",
        "reason": "计算机设",
        "concepts": [],
        "amount": 259925160.0,
        "turnover_rate": 4.91,
        "first_limit_up_time": "11:08:54",
        "last_limit_up_time": "11:08:54",
        "consecutive_boards": 1
      },
      {
        "code": "001230",
        "name": "劲旅环境",
        "reason": "环境治理",
        "concepts": [],
        "amount": 97822555.0,
        "turnover_rate": 5.32,
        "first_limit_up_time": "13:10:54",
        "last_limit_up_time": "13:18:21",
        "consecutive_boards": 1
      },
      {
        "code": "600360",
        "name": "华微电子",
        "reason": "半导体",
        "concepts": [],
        "amount": 2816069408.0,
        "turnover_rate": 19.83,
        "first_limit_up_time": "13:45:08",
        "last_limit_up_time": "14:21:32",
        "consecutive_boards": 1
      }
    ]
  },
  "limit_up_concepts_by_date": {
    "2026-07-03": [
      {
        "concept": "电子纸",
        "concept_code": "301135",
        "change_pct": -2.68,
        "net_inflow_yi": -3.93,
        "count": 1,
        "amount": 321315285.32,
        "rows": [
          {
            "code": "600793",
            "name": "宜宾纸业",
            "reason": "TAC膜+醋酸纤维素+竹基新材料+宜宾国资",
            "concepts": [
              "西部大开发",
              "国企改革",
              "食品安全",
              "电子纸"
            ],
            "amount": 321315285.32,
            "turnover_rate": 9.55,
            "first_limit_up_time": "09:46:37",
            "last_limit_up_time": "09:46:37",
            "consecutive_boards": 5
          }
        ]
      },
      {
        "concept": "食品安全",
        "concept_code": "300023",
        "change_pct": -2.35,
        "net_inflow_yi": -9.68,
        "count": 1,
        "amount": 321315285.32,
        "rows": [
          {
            "code": "600793",
            "name": "宜宾纸业",
            "reason": "TAC膜+醋酸纤维素+竹基新材料+宜宾国资",
            "concepts": [
              "西部大开发",
              "国企改革",
              "食品安全",
              "电子纸"
            ],
            "amount": 321315285.32,
            "turnover_rate": 9.55,
            "first_limit_up_time": "09:46:37",
            "last_limit_up_time": "09:46:37",
            "consecutive_boards": 5
          }
        ]
      },
      {
        "concept": "共同富裕示范区",
        "concept_code": "308732",
        "change_pct": -2.55,
        "net_inflow_yi": -12.72,
        "count": 1,
        "amount": 147152966.0,
        "rows": [
          {
            "code": "603178",
            "name": "圣龙股份",
            "reason": "机器人关节驱动+飞行汽车+泵类龙头",
            "concepts": [
              "减速器",
              "汽车热管理",
              "飞行汽车(eVTOL)",
              "机器人概念",
              "低空经济",
              "长安汽车概念",
              "共同富裕示范区",
              "数字经济",
              "无人驾驶",
              "华为汽车",
              "新能源汽车",
              "比亚迪概念",
              "融资融券",
              "沪股通"
            ],
            "amount": 147152966.0,
            "turnover_rate": 3.89,
            "first_limit_up_time": "09:35:53",
            "last_limit_up_time": "09:35:53",
            "consecutive_boards": 1
          }
        ]
      },
      {
        "concept": "减速器",
        "concept_code": "309000",
        "change_pct": -2.98,
        "net_inflow_yi": -44.06,
        "count": 1,
        "amount": 147152966.0,
        "rows": [
          {
            "code": "603178",
            "name": "圣龙股份",
            "reason": "机器人关节驱动+飞行汽车+泵类龙头",
            "concepts": [
              "减速器",
              "汽车热管理",
              "飞行汽车(eVTOL)",
              "机器人概念",
              "低空经济",
              "长安汽车概念",
              "共同富裕示范区",
              "数字经济",
              "无人驾驶",
              "华为汽车",
              "新能源汽车",
              "比亚迪概念",
              "融资融券",
              "沪股通"
            ],
            "amount": 147152966.0,
            "turnover_rate": 3.89,
            "first_limit_up_time": "09:35:53",
            "last_limit_up_time": "09:35:53",
            "consecutive_boards": 1
          }
        ]
      },
      {
        "concept": "华为汽车",
        "concept_code": "308507",
        "change_pct": -2.64,
        "net_inflow_yi": -37.3,
        "count": 1,
        "amount": 147152966.0,
        "rows": [
          {
            "code": "603178",
            "name": "圣龙股份",
            "reason": "机器人关节驱动+飞行汽车+泵类龙头",
            "concepts": [
              "减速器",
              "汽车热管理",
              "飞行汽车(eVTOL)",
              "机器人概念",
              "低空经济",
              "长安汽车概念",
              "共同富裕示范区",
              "数字经济",
              "无人驾驶",
              "华为汽车",
              "新能源汽车",
              "比亚迪概念",
              "融资融券",
              "沪股通"
            ],
            "amount": 147152966.0,
            "turnover_rate": 3.89,
            "first_limit_up_time": "09:35:53",
            "last_limit_up_time": "09:35:53",
            "consecutive_boards": 1
          }
        ]
      },
      {
        "concept": "汽车热管理",
        "concept_code": "308805",
        "change_pct": -3.06,
        "net_inflow_yi": -31.66,
        "count": 1,
        "amount": 147152966.0,
        "rows": [
          {
            "code": "603178",
            "name": "圣龙股份",
            "reason": "机器人关节驱动+飞行汽车+泵类龙头",
            "concepts": [
              "减速器",
              "汽车热管理",
              "飞行汽车(eVTOL)",
              "机器人概念",
              "低空经济",
              "长安汽车概念",
              "共同富裕示范区",
              "数字经济",
              "无人驾驶",
              "华为汽车",
              "新能源汽车",
              "比亚迪概念",
              "融资融券",
              "沪股通"
            ],
            "amount": 147152966.0,
            "turnover_rate": 3.89,
            "first_limit_up_time": "09:35:53",
            "last_limit_up_time": "09:35:53",
            "consecutive_boards": 1
          }
        ]
      },
      {
        "concept": "飞行汽车(eVTOL)",
        "concept_code": "309113",
        "change_pct": -2.55,
        "net_inflow_yi": -33.37,
        "count": 1,
        "amount": 147152966.0,
        "rows": [
          {
            "code": "603178",
            "name": "圣龙股份",
            "reason": "机器人关节驱动+飞行汽车+泵类龙头",
            "concepts": [
              "减速器",
              "汽车热管理",
              "飞行汽车(eVTOL)",
              "机器人概念",
              "低空经济",
              "长安汽车概念",
              "共同富裕示范区",
              "数字经济",
              "无人驾驶",
              "华为汽车",
              "新能源汽车",
              "比亚迪概念",
              "融资融券",
              "沪股通"
            ],
            "amount": 147152966.0,
            "turnover_rate": 3.89,
            "first_limit_up_time": "09:35:53",
            "last_limit_up_time": "09:35:53",
            "consecutive_boards": 1
          }
        ]
      },
      {
        "concept": "光伏建筑一体化",
        "concept_code": "308729",
        "change_pct": -2.68,
        "net_inflow_yi": -24.02,
        "count": 1,
        "amount": 15183966.01,
        "rows": [
          {
            "code": "603137",
            "name": "恒尚节能",
            "reason": "拟收购存储公司+建筑幕墙+跨界转型",
            "concepts": [
              "装配式建筑",
              "建筑节能",
              "新型城镇化",
              "光伏建筑一体化",
              "股权转让(并购重组)",
              "融资融券"
            ],
            "amount": 15183966.01,
            "turnover_rate": 0.4,
            "first_limit_up_time": "09:25:03",
            "last_limit_up_time": "09:25:03",
            "consecutive_boards": 6
          }
        ]
      },
      {
        "concept": "建筑节能",
        "concept_code": "300261",
        "change_pct": -2.96,
        "net_inflow_yi": -15.57,
        "count": 1,
        "amount": 15183966.01,
        "rows": [
          {
            "code": "603137",
            "name": "恒尚节能",
            "reason": "拟收购存储公司+建筑幕墙+跨界转型",
            "concepts": [
              "装配式建筑",
              "建筑节能",
              "新型城镇化",
              "光伏建筑一体化",
              "股权转让(并购重组)",
              "融资融券"
            ],
            "amount": 15183966.01,
            "turnover_rate": 0.4,
            "first_limit_up_time": "09:25:03",
            "last_limit_up_time": "09:25:03",
            "consecutive_boards": 6
          }
        ]
      },
      {
        "concept": "装配式建筑",
        "concept_code": "305794",
        "change_pct": -3.01,
        "net_inflow_yi": -15.1,
        "count": 1,
        "amount": 15183966.01,
        "rows": [
          {
            "code": "603137",
            "name": "恒尚节能",
            "reason": "拟收购存储公司+建筑幕墙+跨界转型",
            "concepts": [
              "装配式建筑",
              "建筑节能",
              "新型城镇化",
              "光伏建筑一体化",
              "股权转让(并购重组)",
              "融资融券"
            ],
            "amount": 15183966.01,
            "turnover_rate": 0.4,
            "first_limit_up_time": "09:25:03",
            "last_limit_up_time": "09:25:03",
            "consecutive_boards": 6
          }
        ]
      }
    ],
    "2026-07-06": [
      {
        "concept": "存储芯片",
        "concept_code": "307940",
        "change_pct": -1.13,
        "net_inflow_yi": 55.13,
        "count": 1,
        "amount": 4641981027.08,
        "rows": [
          {
            "code": "600246",
            "name": "万通发展",
            "reason": "高速交换芯片+AI算力+PCIe5.0量产",
            "concepts": [
              "存储芯片",
              "芯片概念",
              "5G",
              "毫米波雷达",
              "卫星导航",
              "商业航天",
              "创投",
              "数字经济",
              "京津冀一体化",
              "物业管理",
              "云计算",
              "沪股通",
              "融资融券"
            ],
            "amount": 4641981027.08,
            "turnover_rate": 13.4,
            "first_limit_up_time": "09:48:16",
            "last_limit_up_time": "15:07:34",
            "consecutive_boards": 2
          }
        ]
      },
      {
        "concept": "毫米波雷达",
        "concept_code": "309051",
        "change_pct": -2.66,
        "net_inflow_yi": -12.14,
        "count": 1,
        "amount": 4641981027.08,
        "rows": [
          {
            "code": "600246",
            "name": "万通发展",
            "reason": "高速交换芯片+AI算力+PCIe5.0量产",
            "concepts": [
              "存储芯片",
              "芯片概念",
              "5G",
              "毫米波雷达",
              "卫星导航",
              "商业航天",
              "创投",
              "数字经济",
              "京津冀一体化",
              "物业管理",
              "云计算",
              "沪股通",
              "融资融券"
            ],
            "amount": 4641981027.08,
            "turnover_rate": 13.4,
            "first_limit_up_time": "09:48:16",
            "last_limit_up_time": "15:07:34",
            "consecutive_boards": 2
          }
        ]
      },
      {
        "concept": "物业管理",
        "concept_code": "308717",
        "change_pct": -2.88,
        "net_inflow_yi": -39.84,
        "count": 1,
        "amount": 4641981027.08,
        "rows": [
          {
            "code": "600246",
            "name": "万通发展",
            "reason": "高速交换芯片+AI算力+PCIe5.0量产",
            "concepts": [
              "存储芯片",
              "芯片概念",
              "5G",
              "毫米波雷达",
              "卫星导航",
              "商业航天",
              "创投",
              "数字经济",
              "京津冀一体化",
              "物业管理",
              "云计算",
              "沪股通",
              "融资融券"
            ],
            "amount": 4641981027.08,
            "turnover_rate": 13.4,
            "first_limit_up_time": "09:48:16",
            "last_limit_up_time": "15:07:34",
            "consecutive_boards": 2
          }
        ]
      },
      {
        "concept": "6G概念",
        "concept_code": "309055",
        "change_pct": -2.57,
        "net_inflow_yi": -6.41,
        "count": 1,
        "amount": 1869913047.01,
        "rows": [
          {
            "code": "600288",
            "name": "大恒科技",
            "reason": "机器视觉+机器人+半导体",
            "concepts": [
              "太赫兹",
              "量子科技",
              "机器视觉",
              "专精特新",
              "无人机",
              "6G概念",
              "机器人概念",
              "华为概念",
              "人工智能",
              "元宇宙",
              "芯片概念",
              "腾讯概念",
              "数据要素",
              "AIGC概念",
              "京津冀一体化",
              "智能医疗",
              "宁德时代概念",
              "AI视频",
              "虚拟数字人",
              "华为手机",
              "眼科医疗",
              "期货概念",
              "融资融券",
              "沪股通"
            ],
            "amount": 1869913047.01,
            "turnover_rate": 27.84,
            "first_limit_up_time": "09:34:06",
            "last_limit_up_time": "14:51:48",
            "consecutive_boards": 2
          }
        ]
      },
      {
        "concept": "AI视频",
        "concept_code": "309118",
        "change_pct": -2.43,
        "net_inflow_yi": -4.69,
        "count": 1,
        "amount": 1869913047.01,
        "rows": [
          {
            "code": "600288",
            "name": "大恒科技",
            "reason": "机器视觉+机器人+半导体",
            "concepts": [
              "太赫兹",
              "量子科技",
              "机器视觉",
              "专精特新",
              "无人机",
              "6G概念",
              "机器人概念",
              "华为概念",
              "人工智能",
              "元宇宙",
              "芯片概念",
              "腾讯概念",
              "数据要素",
              "AIGC概念",
              "京津冀一体化",
              "智能医疗",
              "宁德时代概念",
              "AI视频",
              "虚拟数字人",
              "华为手机",
              "眼科医疗",
              "期货概念",
              "融资融券",
              "沪股通"
            ],
            "amount": 1869913047.01,
            "turnover_rate": 27.84,
            "first_limit_up_time": "09:34:06",
            "last_limit_up_time": "14:51:48",
            "consecutive_boards": 2
          }
        ]
      },
      {
        "concept": "元宇宙",
        "concept_code": "308752",
        "change_pct": -2.71,
        "net_inflow_yi": -21.75,
        "count": 1,
        "amount": 1869913047.01,
        "rows": [
          {
            "code": "600288",
            "name": "大恒科技",
            "reason": "机器视觉+机器人+半导体",
            "concepts": [
              "太赫兹",
              "量子科技",
              "机器视觉",
              "专精特新",
              "无人机",
              "6G概念",
              "机器人概念",
              "华为概念",
              "人工智能",
              "元宇宙",
              "芯片概念",
              "腾讯概念",
              "数据要素",
              "AIGC概念",
              "京津冀一体化",
              "智能医疗",
              "宁德时代概念",
              "AI视频",
              "虚拟数字人",
              "华为手机",
              "眼科医疗",
              "期货概念",
              "融资融券",
              "沪股通"
            ],
            "amount": 1869913047.01,
            "turnover_rate": 27.84,
            "first_limit_up_time": "09:34:06",
            "last_limit_up_time": "14:51:48",
            "consecutive_boards": 2
          }
        ]
      },
      {
        "concept": "华为手机",
        "concept_code": "309167",
        "change_pct": -2.52,
        "net_inflow_yi": -11.26,
        "count": 1,
        "amount": 1869913047.01,
        "rows": [
          {
            "code": "600288",
            "name": "大恒科技",
            "reason": "机器视觉+机器人+半导体",
            "concepts": [
              "太赫兹",
              "量子科技",
              "机器视觉",
              "专精特新",
              "无人机",
              "6G概念",
              "机器人概念",
              "华为概念",
              "人工智能",
              "元宇宙",
              "芯片概念",
              "腾讯概念",
              "数据要素",
              "AIGC概念",
              "京津冀一体化",
              "智能医疗",
              "宁德时代概念",
              "AI视频",
              "虚拟数字人",
              "华为手机",
              "眼科医疗",
              "期货概念",
              "融资融券",
              "沪股通"
            ],
            "amount": 1869913047.01,
            "turnover_rate": 27.84,
            "first_limit_up_time": "09:34:06",
            "last_limit_up_time": "14:51:48",
            "consecutive_boards": 2
          }
        ]
      },
      {
        "concept": "太赫兹",
        "concept_code": "300795",
        "change_pct": -3.32,
        "net_inflow_yi": -11.72,
        "count": 1,
        "amount": 1869913047.01,
        "rows": [
          {
            "code": "600288",
            "name": "大恒科技",
            "reason": "机器视觉+机器人+半导体",
            "concepts": [
              "太赫兹",
              "量子科技",
              "机器视觉",
              "专精特新",
              "无人机",
              "6G概念",
              "机器人概念",
              "华为概念",
              "人工智能",
              "元宇宙",
              "芯片概念",
              "腾讯概念",
              "数据要素",
              "AIGC概念",
              "京津冀一体化",
              "智能医疗",
              "宁德时代概念",
              "AI视频",
              "虚拟数字人",
              "华为手机",
              "眼科医疗",
              "期货概念",
              "融资融券",
              "沪股通"
            ],
            "amount": 1869913047.01,
            "turnover_rate": 27.84,
            "first_limit_up_time": "09:34:06",
            "last_limit_up_time": "14:51:48",
            "consecutive_boards": 2
          }
        ]
      },
      {
        "concept": "期货概念",
        "concept_code": "300220",
        "change_pct": -2.31,
        "net_inflow_yi": -60.18,
        "count": 1,
        "amount": 1869913047.01,
        "rows": [
          {
            "code": "600288",
            "name": "大恒科技",
            "reason": "机器视觉+机器人+半导体",
            "concepts": [
              "太赫兹",
              "量子科技",
              "机器视觉",
              "专精特新",
              "无人机",
              "6G概念",
              "机器人概念",
              "华为概念",
              "人工智能",
              "元宇宙",
              "芯片概念",
              "腾讯概念",
              "数据要素",
              "AIGC概念",
              "京津冀一体化",
              "智能医疗",
              "宁德时代概念",
              "AI视频",
              "虚拟数字人",
              "华为手机",
              "眼科医疗",
              "期货概念",
              "融资融券",
              "沪股通"
            ],
            "amount": 1869913047.01,
            "turnover_rate": 27.84,
            "first_limit_up_time": "09:34:06",
            "last_limit_up_time": "14:51:48",
            "consecutive_boards": 2
          }
        ]
      },
      {
        "concept": "眼科医疗",
        "concept_code": "301252",
        "change_pct": -3.16,
        "net_inflow_yi": -29.06,
        "count": 1,
        "amount": 1869913047.01,
        "rows": [
          {
            "code": "600288",
            "name": "大恒科技",
            "reason": "机器视觉+机器人+半导体",
            "concepts": [
              "太赫兹",
              "量子科技",
              "机器视觉",
              "专精特新",
              "无人机",
              "6G概念",
              "机器人概念",
              "华为概念",
              "人工智能",
              "元宇宙",
              "芯片概念",
              "腾讯概念",
              "数据要素",
              "AIGC概念",
              "京津冀一体化",
              "智能医疗",
              "宁德时代概念",
              "AI视频",
              "虚拟数字人",
              "华为手机",
              "眼科医疗",
              "期货概念",
              "融资融券",
              "沪股通"
            ],
            "amount": 1869913047.01,
            "turnover_rate": 27.84,
            "first_limit_up_time": "09:34:06",
            "last_limit_up_time": "14:51:48",
            "consecutive_boards": 2
          }
        ]
      },
      {
        "concept": "虚拟数字人",
        "concept_code": "308794",
        "change_pct": -2.46,
        "net_inflow_yi": -15.98,
        "count": 1,
        "amount": 1869913047.01,
        "rows": [
          {
            "code": "600288",
            "name": "大恒科技",
            "reason": "机器视觉+机器人+半导体",
            "concepts": [
              "太赫兹",
              "量子科技",
              "机器视觉",
              "专精特新",
              "无人机",
              "6G概念",
              "机器人概念",
              "华为概念",
              "人工智能",
              "元宇宙",
              "芯片概念",
              "腾讯概念",
              "数据要素",
              "AIGC概念",
              "京津冀一体化",
              "智能医疗",
              "宁德时代概念",
              "AI视频",
              "虚拟数字人",
              "华为手机",
              "眼科医疗",
              "期货概念",
              "融资融券",
              "沪股通"
            ],
            "amount": 1869913047.01,
            "turnover_rate": 27.84,
            "first_limit_up_time": "09:34:06",
            "last_limit_up_time": "14:51:48",
            "consecutive_boards": 2
          }
        ]
      },
      {
        "concept": "量子科技",
        "concept_code": "300830",
        "change_pct": -2.55,
        "net_inflow_yi": -2.76,
        "count": 1,
        "amount": 1869913047.01,
        "rows": [
          {
            "code": "600288",
            "name": "大恒科技",
            "reason": "机器视觉+机器人+半导体",
            "concepts": [
              "太赫兹",
              "量子科技",
              "机器视觉",
              "专精特新",
              "无人机",
              "6G概念",
              "机器人概念",
              "华为概念",
              "人工智能",
              "元宇宙",
              "芯片概念",
              "腾讯概念",
              "数据要素",
              "AIGC概念",
              "京津冀一体化",
              "智能医疗",
              "宁德时代概念",
              "AI视频",
              "虚拟数字人",
              "华为手机",
              "眼科医疗",
              "期货概念",
              "融资融券",
              "沪股通"
            ],
            "amount": 1869913047.01,
            "turnover_rate": 27.84,
            "first_limit_up_time": "09:34:06",
            "last_limit_up_time": "14:51:48",
            "consecutive_boards": 2
          }
        ]
      },
      {
        "concept": "参股银行",
        "concept_code": "301270",
        "change_pct": -2.51,
        "net_inflow_yi": -28.89,
        "count": 1,
        "amount": 1383427145.57,
        "rows": [
          {
            "code": "002457",
            "name": "青龙管业",
            "reason": "其他",
            "concepts": [
              "地下管网",
              "新型城镇化",
              "水利",
              "乡村振兴",
              "参股银行",
              "京津冀一体化",
              "互联网金融",
              "新疆振兴",
              "西部大开发",
              "风电"
            ],
            "amount": 1383427145.57,
            "turnover_rate": 27.74,
            "first_limit_up_time": "09:30:27",
            "last_limit_up_time": "09:30:27",
            "consecutive_boards": 0
          }
        ]
      },
      {
        "concept": "地下管网",
        "concept_code": "301623",
        "change_pct": -2.35,
        "net_inflow_yi": -11.61,
        "count": 1,
        "amount": 1383427145.57,
        "rows": [
          {
            "code": "002457",
            "name": "青龙管业",
            "reason": "其他",
            "concepts": [
              "地下管网",
              "新型城镇化",
              "水利",
              "乡村振兴",
              "参股银行",
              "京津冀一体化",
              "互联网金融",
              "新疆振兴",
              "西部大开发",
              "风电"
            ],
            "amount": 1383427145.57,
            "turnover_rate": 27.74,
            "first_limit_up_time": "09:30:27",
            "last_limit_up_time": "09:30:27",
            "consecutive_boards": 0
          }
        ]
      },
      {
        "concept": "新疆振兴",
        "concept_code": "300386",
        "change_pct": -2.77,
        "net_inflow_yi": -38.75,
        "count": 1,
        "amount": 1383427145.57,
        "rows": [
          {
            "code": "002457",
            "name": "青龙管业",
            "reason": "其他",
            "concepts": [
              "地下管网",
              "新型城镇化",
              "水利",
              "乡村振兴",
              "参股银行",
              "京津冀一体化",
              "互联网金融",
              "新疆振兴",
              "西部大开发",
              "风电"
            ],
            "amount": 1383427145.57,
            "turnover_rate": 27.74,
            "first_limit_up_time": "09:30:27",
            "last_limit_up_time": "09:30:27",
            "consecutive_boards": 0
          }
        ]
      },
      {
        "concept": "丙烯酸",
        "concept_code": "305376",
        "change_pct": -2.74,
        "net_inflow_yi": -12.07,
        "count": 1,
        "amount": 881085542.32,
        "rows": [
          {
            "code": "603722",
            "name": "阿科力",
            "reason": "其他",
            "concepts": [
              "丙烯酸",
              "专精特新",
              "人民币贬值受益",
              "燃料电池"
            ],
            "amount": 881085542.32,
            "turnover_rate": 19.64,
            "first_limit_up_time": "09:25:03",
            "last_limit_up_time": "09:32:27",
            "consecutive_boards": 0
          }
        ]
      },
      {
        "concept": "华为数字能源",
        "concept_code": "309169",
        "change_pct": -2.59,
        "net_inflow_yi": -13.47,
        "count": 1,
        "amount": 667597133.35,
        "rows": [
          {
            "code": "603861",
            "name": "白云电器",
            "reason": "变压器出海+AIDC直流配电+电网设备",
            "concepts": [
              "柔性直流输电",
              "智能电网",
              "华为数字能源",
              "特高压",
              "东数西算(算力)",
              "核电",
              "数据中心(AIDC)",
              "一带一路",
              "储能",
              "华为概念",
              "新能源汽车",
              "光伏概念",
              "宁德时代概念",
              "沪股通"
            ],
            "amount": 667597133.35,
            "turnover_rate": 8.51,
            "first_limit_up_time": "09:51:21",
            "last_limit_up_time": "10:01:33",
            "consecutive_boards": 2
          }
        ]
      },
      {
        "concept": "柔性直流输电",
        "concept_code": "308810",
        "change_pct": -2.77,
        "net_inflow_yi": -22.63,
        "count": 1,
        "amount": 667597133.35,
        "rows": [
          {
            "code": "603861",
            "name": "白云电器",
            "reason": "变压器出海+AIDC直流配电+电网设备",
            "concepts": [
              "柔性直流输电",
              "智能电网",
              "华为数字能源",
              "特高压",
              "东数西算(算力)",
              "核电",
              "数据中心(AIDC)",
              "一带一路",
              "储能",
              "华为概念",
              "新能源汽车",
              "光伏概念",
              "宁德时代概念",
              "沪股通"
            ],
            "amount": 667597133.35,
            "turnover_rate": 8.51,
            "first_limit_up_time": "09:51:21",
            "last_limit_up_time": "10:01:33",
            "consecutive_boards": 2
          }
        ]
      },
      {
        "concept": "特高压",
        "concept_code": "300353",
        "change_pct": -2.62,
        "net_inflow_yi": -37.2,
        "count": 1,
        "amount": 667597133.35,
        "rows": [
          {
            "code": "603861",
            "name": "白云电器",
            "reason": "变压器出海+AIDC直流配电+电网设备",
            "concepts": [
              "柔性直流输电",
              "智能电网",
              "华为数字能源",
              "特高压",
              "东数西算(算力)",
              "核电",
              "数据中心(AIDC)",
              "一带一路",
              "储能",
              "华为概念",
              "新能源汽车",
              "光伏概念",
              "宁德时代概念",
              "沪股通"
            ],
            "amount": 667597133.35,
            "turnover_rate": 8.51,
            "first_limit_up_time": "09:51:21",
            "last_limit_up_time": "10:01:33",
            "consecutive_boards": 2
          }
        ]
      },
      {
        "concept": "安防",
        "concept_code": "300800",
        "change_pct": -2.5,
        "net_inflow_yi": -17.02,
        "count": 1,
        "amount": 539335355.3,
        "rows": [
          {
            "code": "603819",
            "name": "神力股份",
            "reason": "其他",
            "concepts": [
              "安防",
              "新能源汽车",
              "风电",
              "股权转让(并购重组)"
            ],
            "amount": 539335355.3,
            "turnover_rate": 17.24,
            "first_limit_up_time": "09:31:11",
            "last_limit_up_time": "09:48:38",
            "consecutive_boards": 0
          }
        ]
      },
      {
        "concept": "电子纸",
        "concept_code": "301135",
        "change_pct": -2.68,
        "net_inflow_yi": -3.93,
        "count": 1,
        "amount": 321315285.32,
        "rows": [
          {
            "code": "600793",
            "name": "宜宾纸业",
            "reason": "TAC膜+醋酸纤维素+竹基新材料+宜宾国资",
            "concepts": [
              "西部大开发",
              "国企改革",
              "食品安全",
              "电子纸"
            ],
            "amount": 321315285.32,
            "turnover_rate": 9.55,
            "first_limit_up_time": "09:46:37",
            "last_limit_up_time": "09:46:37",
            "consecutive_boards": 5
          }
        ]
      },
      {
        "concept": "食品安全",
        "concept_code": "300023",
        "change_pct": -2.35,
        "net_inflow_yi": -9.68,
        "count": 1,
        "amount": 321315285.32,
        "rows": [
          {
            "code": "600793",
            "name": "宜宾纸业",
            "reason": "TAC膜+醋酸纤维素+竹基新材料+宜宾国资",
            "concepts": [
              "西部大开发",
              "国企改革",
              "食品安全",
              "电子纸"
            ],
            "amount": 321315285.32,
            "turnover_rate": 9.55,
            "first_limit_up_time": "09:46:37",
            "last_limit_up_time": "09:46:37",
            "consecutive_boards": 5
          }
        ]
      },
      {
        "concept": "光伏建筑一体化",
        "concept_code": "308729",
        "change_pct": -2.68,
        "net_inflow_yi": -24.02,
        "count": 1,
        "amount": 15183966.01,
        "rows": [
          {
            "code": "603137",
            "name": "恒尚节能",
            "reason": "拟收购存储公司+建筑幕墙+跨界转型",
            "concepts": [
              "装配式建筑",
              "建筑节能",
              "新型城镇化",
              "光伏建筑一体化",
              "股权转让(并购重组)",
              "融资融券"
            ],
            "amount": 15183966.01,
            "turnover_rate": 0.4,
            "first_limit_up_time": "09:25:03",
            "last_limit_up_time": "09:25:03",
            "consecutive_boards": 6
          }
        ]
      },
      {
        "concept": "建筑节能",
        "concept_code": "300261",
        "change_pct": -2.96,
        "net_inflow_yi": -15.57,
        "count": 1,
        "amount": 15183966.01,
        "rows": [
          {
            "code": "603137",
            "name": "恒尚节能",
            "reason": "拟收购存储公司+建筑幕墙+跨界转型",
            "concepts": [
              "装配式建筑",
              "建筑节能",
              "新型城镇化",
              "光伏建筑一体化",
              "股权转让(并购重组)",
              "融资融券"
            ],
            "amount": 15183966.01,
            "turnover_rate": 0.4,
            "first_limit_up_time": "09:25:03",
            "last_limit_up_time": "09:25:03",
            "consecutive_boards": 6
          }
        ]
      },
      {
        "concept": "装配式建筑",
        "concept_code": "305794",
        "change_pct": -3.01,
        "net_inflow_yi": -15.1,
        "count": 1,
        "amount": 15183966.01,
        "rows": [
          {
            "code": "603137",
            "name": "恒尚节能",
            "reason": "拟收购存储公司+建筑幕墙+跨界转型",
            "concepts": [
              "装配式建筑",
              "建筑节能",
              "新型城镇化",
              "光伏建筑一体化",
              "股权转让(并购重组)",
              "融资融券"
            ],
            "amount": 15183966.01,
            "turnover_rate": 0.4,
            "first_limit_up_time": "09:25:03",
            "last_limit_up_time": "09:25:03",
            "consecutive_boards": 6
          }
        ]
      }
    ],
    "2026-07-07": []
  }
}